coniii/LICENSE.txt
coniii/__init__.py
coniii/entropy.py
coniii/enumerate.py
coniii/enumerate_potts.py
coniii/mean_field_ising.py
coniii/models.py
coniii/pseudo_inverse_ising.py
coniii/samplers.py
coniii/samplers_ext.cpython-310-x86_64-linux-gnu.so
coniii/solvers.py
coniii/test_enumerate.py
coniii/test_enumerate_potts.py
coniii/test_samplers.py
coniii/test_solvers.py
coniii/test_utils.py
coniii/usage_guide.ipynb
coniii/utils.py
coniii/version.py
coniii/ising/__init__.py
coniii/ising/automaton.py
coniii/ising/test_utils.py
coniii/ising/utils.py
coniii/ising_eqn/__init__.py
coniii/ising_eqn/ising_eqn_12_sym_hp.py
coniii/ising_eqn/ising_eqn_2.py
coniii/ising_eqn/ising_eqn_2_sym.py
coniii/ising_eqn/ising_eqn_3.py
coniii/ising_eqn/ising_eqn_3_sym.py
coniii/ising_eqn/ising_eqn_4.py
coniii/ising_eqn/ising_eqn_4_sym.py
coniii/ising_eqn/ising_eqn_4_sym_hp.py
coniii/ising_eqn/ising_eqn_5.py
coniii/ising_eqn/ising_eqn_5_sym.py
coniii/ising_eqn/ising_eqn_5_sym_triplet.py
coniii/ising_eqn/ising_eqn_5_triplet.py
coniii/ising_eqn/ising_eqn_6.py
coniii/ising_eqn/ising_eqn_6_sym.py
coniii/ising_eqn/ising_eqn_7.py
coniii/ising_eqn/ising_eqn_7_sym.py
coniii/ising_eqn/ising_eqn_8.py
coniii/ising_eqn/ising_eqn_8_sym.py
coniii/ising_eqn/ising_eqn_9.py
coniii/ising_eqn/ising_eqn_9_sym.py
coniii/ising_eqn/ising_eqn_9_sym_hp.py
coniii-3.0.1.dist-info/LICENSE.txt
coniii-3.0.1.dist-info/METADATA
coniii-3.0.1.dist-info/WHEEL
coniii-3.0.1.dist-info/top_level.txt
coniii-3.0.1.dist-info/RECORD
