Metadata-Version: 2.1
Name: coniii
Version: 3.0.1
Summary: Convenient Interface to Inverse Ising (ConIII)
Home-page: https://github.com/eltrompetero/coniii
Author: Edward D. Lee, Bryan C Daniels
Author-email: edlee@santafe.edu
License: MIT
Keywords: inverse Ising maxent maximum entropy inference
Classifier: Development Status :: 5 - Production/Stable
Classifier: Intended Audience :: Science/Research
Classifier: Topic :: Scientific/Engineering :: Information Analysis
Classifier: License :: OSI Approved :: MIT License
Classifier: Programming Language :: Python :: 3 :: Only
Requires-Python: >=3.8.3
License-File: LICENSE.txt
Requires-Dist: multiprocess (<1,>=0.70.7)
Requires-Dist: scipy
Requires-Dist: matplotlib
Requires-Dist: numpy (<2,>=1.16.2)
Requires-Dist: numba (<1,>=0.45.1)
Requires-Dist: mpmath (>=1.1.0)
Requires-Dist: dill
